{
  "main": {
    "id": "2db863be6a059e20",
    "type": "split",
    "children": [
      {
        "id": "65e517085ea3972c",
        "type": "tabs",
        "children": [
          {
            "id": "dda2b30ad78083c5",
            "type": "leaf",
            "state": {
              "type": "markdown",
              "state": {
                "file": "Linux/nmcli.md",
                "mode": "source",
                "source": false
              },
              "icon": "lucide-file",
              "title": "nmcli"
            }
          }
        ]
      }
    ],
    "direction": "vertical"
  },
  "left": {
    "id": "5eeaa5c2a937f7f3",
    "type": "split",
    "children": [
      {
        "id": "66c37fa2883a181c",
        "type": "tabs",
        "children": [
          {
            "id": "6cc727f675c2e211",
            "type": "leaf",
            "state": {
              "type": "file-explorer",
              "state": {
                "sortOrder": "alphabetical",
                "autoReveal": false
              },
              "icon": "lucide-folder-closed",
              "title": "Files"
            }
          },
          {
            "id": "1488ede307c9b552",
            "type": "leaf",
            "state": {
              "type": "search",
              "state": {
                "query": "",
                "matchingCase": false,
                "explainSearch": false,
                "collapseAll": false,
                "extraContext": false,
                "sortOrder": "alphabetical"
              },
              "icon": "lucide-search",
              "title": "Buscar"
            }
          },
          {
            "id": "7ec2b7e0a9435238",
            "type": "leaf",
            "state": {
              "type": "bookmarks",
              "state": {},
              "icon": "lucide-bookmark",
              "title": "Marcadores"
            }
          }
        ]
      }
    ],
    "direction": "horizontal",
    "width": 305.50634002685547
  },
  "right": {
    "id": "7cdbf33181f023a8",
    "type": "split",
    "children": [
      {
        "id": "22d92fee5a1f7a63",
        "type": "tabs",
        "children": [
          {
            "id": "b8d61337aba9d80a",
            "type": "leaf",
            "state": {
              "type": "backlink",
              "state": {
                "file": "Distribuciones probadas.md",
                "collapseAll": false,
                "extraContext": false,
                "sortOrder": "alphabetical",
                "showSearch": false,
                "searchQuery": "",
                "backlinkCollapsed": false,
                "unlinkedCollapsed": true
              },
              "icon": "links-coming-in",
              "title": "Enlaces entrantes de Distribuciones probadas"
            }
          },
          {
            "id": "3680e2ec82fa4e93",
            "type": "leaf",
            "state": {
              "type": "outgoing-link",
              "state": {
                "file": "Distribuciones probadas.md",
                "linksCollapsed": false,
                "unlinkedCollapsed": true
              },
              "icon": "links-going-out",
              "title": "Enlaces salientes de Distribuciones probadas"
            }
          },
          {
            "id": "73872f766020d894",
            "type": "leaf",
            "state": {
              "type": "tag",
              "state": {
                "sortOrder": "frequency",
                "useHierarchy": true,
                "showSearch": false,
                "searchQuery": ""
              },
              "icon": "lucide-tags",
              "title": "Etiquetas"
            }
          },
          {
            "id": "2cd855b827af197a",
            "type": "leaf",
            "state": {
              "type": "outline",
              "state": {
                "file": "Distribuciones probadas.md",
                "followCursor": false,
                "showSearch": false,
                "searchQuery": ""
              },
              "icon": "lucide-list",
              "title": "Esquema de Distribuciones probadas"
            }
          }
        ]
      }
    ],
    "direction": "horizontal",
    "width": 300,
    "collapsed": true
  },
  "left-ribbon": {
    "hiddenItems": {
      "switcher:Open quick switcher": false,
      "graph:Open graph view": false,
      "canvas:Create new canvas": false,
      "daily-notes:Open today's daily note": false,
      "templates:Insert template": false,
      "command-palette:Open command palette": false,
      "bases:Create new base": false
    }
  },
  "active": "dda2b30ad78083c5",
  "lastOpenFiles": [
    "Linux/nanorc.md",
    "Linux/Instalar .deb.md",
    "Linux/Instalar .tar.gz.md",
    "Linux/Desempaquetar un AppImage.md",
    "Linux/Instalar tar.bz2.md",
    "Linux/nmcli.md",
    "Linux/Git does not allow to make a push in a repositori.md",
    "Linux/Enable scroll in browsers for Linux.md",
    "Linux/Distribuciones probadas.md",
    "Linux/Desinstalar distribución Linux.md",
    "Linux/Conky.md",
    "Linux/Checksum de linux.md",
    "Linux/Buetooth.md",
    "Linux/Cambiar el nombre de la computadora.md",
    "Linux/Change theme on Plank.md",
    "Linux/Repositorio pide contraseña.md",
    "Linux/Removing Firefox.md",
    "Comandos de docker.md",
    "Comandos de git.md",
    "Configuraciones de bash.md",
    "Git push requires a token.md",
    "Time changed in Windows dual boot with Linux.md",
    "README.md",
    "Linux/Instalar python.md",
    "Linux/XZ.md",
    "Linux/Venv in Linux.md",
    "Windows",
    "Linux"
  ]
}